seeq_sysid/__init__.py
seeq_sysid/__main__.py
seeq_sysid/_copy.py
seeq_sysid/_version.py
seeq_sysid/app.py
seeq_sysid/data/seeq_logo.png
seeq_sysid/deployment_notebook/sysid_notebook.ipynb
seeq_sysid/gui/__init__.py
seeq_sysid/gui/_backend.py
seeq_sysid/gui/app_bar.py
seeq_sysid/gui/app_sheet.py
seeq_sysid/gui/data_editor.py
seeq_sysid/gui/figure_card.py
seeq_sysid/gui/figure_table.py
seeq_sysid/gui/panels.py
seeq_sysid/gui/setup.py
seeq_sysid/gui/table_card.py
seeq_sysid/gui/transfer_card_result.py
seeq_sysid/gui/transfer_card_setup.py
seeq_sysid/gui/transfer_chip.py
seeq_sysid/gui/transfer_matrix.py
seeq_sysid/gui/utils.py
seeq_sysid/model/__init__.py
seeq_sysid/model/arx.py
seeq_sysid/model/base.py
seeq_sysid/model/nn.py
seeq_sysid/model/ss.py
seeq_sysid/model/tf.py
seeq_sysid/model/tf_item.py
seeq_sysid/model/utils.py
seeq_sysid-1.0.1.dist-info/LICENSE
seeq_sysid-1.0.1.dist-info/METADATA
seeq_sysid-1.0.1.dist-info/WHEEL
seeq_sysid-1.0.1.dist-info/top_level.txt
seeq_sysid-1.0.1.dist-info/RECORD
