Metadata-Version: 2.1
Name: seeq-sysid
Version: 1.0.1
Summary: Seeq System Identification Addon
Home-page: https://github.com/BYU-PRISM/Seeq
Author: Junho Park, Mohammad Reza Babaei
Author-email: jnho.park@gmail.com, babaei_mr@outlook.com
License: MIT
Keywords: Seeq Prism System Identification ARX FIR ARIMAX Subspace State-Space Neural-Network Addon Time-Series Transfer Function
Platform: UNKNOWN
Classifier: License :: OSI Approved :: MIT License
Classifier: Programming Language :: Python
Requires-Dist: ipyvuetify (>=1.5.1)
Requires-Dist: gekko (>=1.0.6)
Requires-Dist: numpy
Requires-Dist: pandas (<2.0.0,>=1.2.1)
Requires-Dist: plotly (>=5.10.0)
Requires-Dist: python-dateutil (>=2.8.1)
Requires-Dist: tensorflow (>=2.5)
Requires-Dist: keras-tuner (==1.0.4)
Requires-Dist: scipy
Requires-Dist: protobuf (~=3.20)
